lcd1602gpio.py
lcd1602gpio-0.3.1.dist-info/LICENSE
lcd1602gpio-0.3.1.dist-info/METADATA
lcd1602gpio-0.3.1.dist-info/WHEEL
lcd1602gpio-0.3.1.dist-info/top_level.txt
lcd1602gpio-0.3.1.dist-info/RECORD
