Metadata-Version: 2.1
Name: lcd1602gpio
Version: 0.3.1
Summary: Use HD44780-compatible 16x2 LCD module via RPi.GPIO
Home-page: https://github.com/alextwl/lcd1602gpio
Author: Wei-Li Tang
Author-email: alextwl@gmail.com
Classifier: Programming Language :: Python :: 3
Classifier: License :: OSI Approved :: MIT License
Classifier: Operating System :: POSIX :: Linux
Classifier: Topic :: System :: Hardware
License-File: LICENSE
Requires-Dist: RPi.GPIO >=0.7.0
